axes_login_actions/__init__.py
axes_login_actions/apps.py
axes_login_actions/models.py
axes_login_actions/signals.py
axes_login_actions/actions/__init__.py
axes_login_actions/actions/email.py
axes_login_actions/actions/email.pyc
axes_login_actions/templates/axes_login_actions/email_notify.txt
django_axes_login_actions-1.3.0.dist-info/LICENSE
django_axes_login_actions-1.3.0.dist-info/METADATA
django_axes_login_actions-1.3.0.dist-info/WHEEL
django_axes_login_actions-1.3.0.dist-info/top_level.txt
django_axes_login_actions-1.3.0.dist-info/RECORD
