Metadata-Version: 2.1
Name: django-axes-login-actions
Version: 1.3.0
Summary: Perform one or more actions if someone performed a login, e.g. to the admin interface.
Home-page: https://github.com/eht16/django-axes-login-actions
Author: Enrico Tröger
Author-email: enrico.troeger@uvena.de
Maintainer: Enrico Tröger
Maintainer-email: enrico.troeger@uvena.de
License: MIT
Keywords: django,security,authentication
Platform: UNKNOWN
Classifier: Development Status :: 5 - Production/Stable
Classifier: Environment :: Web Environment
Classifier: Framework :: Django
Classifier: Intended Audience :: Developers
Classifier: Intended Audience :: System Administrators
Classifier: License :: OSI Approved :: BSD License
Classifier: Operating System :: OS Independent
Classifier: Programming Language :: Python
Classifier: Topic :: Internet :: Log Analysis
Classifier: Topic :: Internet :: WWW/HTTP :: WSGI :: Middleware
Classifier: Topic :: Security
Classifier: Topic :: System :: Logging
Requires-Dist: django-axes
